{
  "generated_at": "2026-03-19T07:09:44.772Z",
  "headlines": [
    {
      "title": "Signal spike detected across multiple regions",
      "region": "World"
    },
    {
      "title": "Logistics anomalies near key hubs",
      "region": "Europe"
    },
    {
      "title": "Macro prints shift risk appetite",
      "region": "Markets"
    }
  ],
  "map_points": [
    {
      "lat": 52.52,
      "lon": 13.405,
      "title": "Berlin: Signal spike",
      "kind": "news"
    },
    {
      "lat": 40.64,
      "lon": -73.78,
      "title": "Top flight: widebody",
      "kind": "flight"
    },
    {
      "lat": 1.2,
      "lon": 103.8,
      "title": "Top vessel presence",
      "kind": "ship"
    }
  ],
  "markets": {
    "gold_usd": 153776.69933027725,
    "btc_usd": 70317.5,
    "wti_usd": 96.67,
    "brent_usd": 114.43
  }
}
